<?xml version="1.0" encoding="utf-8"?>
<VARIANT>
 </AIF/CL_CI_TEST_AIFC_APPLOG>
  <VERSION>000</VERSION>
  <ATTRIBUTES/>
 <//AIF/CL_CI_TEST_AIFC_APPLOG>
 </AIF/CL_CI_TEST_AIFC_IFDET>
  <VERSION>000</VERSION>
  <ATTRIBUTES/>
 <//AIF/CL_CI_TEST_AIFC_IFDET>
 </AIF/CL_CI_TEST_AIFC_TRANS>
  <VERSION>000</VERSION>
  <ATTRIBUTES/>
 <//AIF/CL_CI_TEST_AIFC_TRANS>
 <CL_CI_AMC_ATC_CHECK>
  <VERSION>000</VERSION>
  <ATTRIBUTES/>
 </CL_CI_AMC_ATC_CHECK>
 <CL_CI_APC_ATC_CHECK>
  <VERSION>000</VERSION>
  <ATTRIBUTES/>
 </CL_CI_APC_ATC_CHECK>
 <CL_CI_CDS_WARNINGS>
  <VERSION>000</VERSION>
  <ATTRIBUTES/>
 </CL_CI_CDS_WARNINGS>
 <CL_CI_CHK_ABAP_USAGE_SQL_VIEW>
  <VERSION>000</VERSION>
  <ATTRIBUTES>
   <CHECK_MESSAGE_IDS/>
  </ATTRIBUTES>
 </CL_CI_CHK_ABAP_USAGE_SQL_VIEW>
 <CL_CI_CHK_DDIC_USAGE_SQL_VIEW>
  <VERSION>000</VERSION>
  <ATTRIBUTES>
   <CHECK_MESSAGE_IDS/>
  </ATTRIBUTES>
 </CL_CI_CHK_DDIC_USAGE_SQL_VIEW>
 <CL_CI_DDIC_CHECK_LOGGING>
  <VERSION>000</VERSION>
  <ATTRIBUTES/>
 </CL_CI_DDIC_CHECK_LOGGING>
 <CL_CI_TEST_ANALYZE_SELECT_HANA>
  <VERSION>000</VERSION>
  <ATTRIBUTES>
   <PA_BUFF>X</PA_BUFF>
   <PA_COMPONENTS>2 </PA_COMPONENTS>
   <PA_DEBUG></PA_DEBUG>
   <PA_DETAIL></PA_DETAIL>
   <PA_EFFORT_ASSIGNS>20 </PA_EFFORT_ASSIGNS>
   <PA_EFFORT_COLUMNS_ACC>10 </PA_EFFORT_COLUMNS_ACC>
   <PA_FULLNAME></PA_FULLNAME>
   <PA_LEVEL_EXTERN>1 </PA_LEVEL_EXTERN>
   <PA_NO_TRANS></PA_NO_TRANS>
   <PA_ONLY_LOCAL>X</PA_ONLY_LOCAL>
   <PA_PERCENT>20 </PA_PERCENT>
   <PA_TABKAT>0 </PA_TABKAT>
   <PA_TABLES/>
  </ATTRIBUTES>
 </CL_CI_TEST_ANALYZE_SELECT_HANA>
 <CL_CI_TEST_APPEND_TO_SORTED>
  <VERSION>000</VERSION>
  <ATTRIBUTES/>
 </CL_CI_TEST_APPEND_TO_SORTED>
 <CL_CI_TEST_CALL_TRANS_WITH>
  <VERSION>000</VERSION>
  <ATTRIBUTES/>
 </CL_CI_TEST_CALL_TRANS_WITH>
 <CL_CI_TEST_CDS_BEH_EVENTS>
  <VERSION>000</VERSION>
  <ATTRIBUTES/>
 </CL_CI_TEST_CDS_BEH_EVENTS>
 <CL_CI_TEST_CDS_COMPLEXITY>
  <VERSION>000</VERSION>
  <ATTRIBUTES>
   <ATTRIBUTE_NUMBER_OF_TABLES>225 </ATTRIBUTE_NUMBER_OF_TABLES>
  </ATTRIBUTES>
 </CL_CI_TEST_CDS_COMPLEXITY>
 <CL_CI_TEST_CDS_SYNTAX_REM>
  <VERSION>000</VERSION>
  <ATTRIBUTES/>
 </CL_CI_TEST_CDS_SYNTAX_REM>
 <CL_CI_TEST_CRITICAL_STATEMENTS>
  <VERSION>002</VERSION>
  <ATTRIBUTES>
   <CALLTA>X</CALLTA>
   <CCALL>X</CCALL>
   <EDITORCALL>X</EDITORCALL>
   <EXECSQL>X</EXECSQL>
   <EXPORTDYNP>X</EXPORTDYNP>
   <EXPORTNAM>X</EXPORTNAM>
   <GENERATE>X</GENERATE>
   <HINTS>X</HINTS>
   <IMPORTDYNP></IMPORTDYNP>
   <IMPORTNAM></IMPORTNAM>
   <INSERTREP>X</INSERTREP>
   <READREP>X</READREP>
   <ROLLBACK>X</ROLLBACK>
   <SUBMIT>X</SUBMIT>
   <SYSTEMCALL>X</SYSTEMCALL>
  </ATTRIBUTES>
 </CL_CI_TEST_CRITICAL_STATEMENTS>
 <CL_CI_TEST_DB_OPS_IN_LOOPS>
  <VERSION>000</VERSION>
  <ATTRIBUTES>
   <PA_BUFF>X</PA_BUFF>
   <PA_CHECK_EXEC_SQL>X</PA_CHECK_EXEC_SQL>
   <PA_CHECK_READING>X</PA_CHECK_READING>
   <PA_CHECK_WRITING>X</PA_CHECK_WRITING>
   <PA_DEPTH>3 </PA_DEPTH>
   <PA_EFFORT_CALLS>20 </PA_EFFORT_CALLS>
   <PA_EFFORT_LOOP>10 </PA_EFFORT_LOOP>
   <PA_LOCAL>X</PA_LOCAL>
   <PA_MAX_STACKS>10 </PA_MAX_STACKS>
   <PA_TABKAT>0 </PA_TABKAT>
   <PA_TABLES/>
  </ATTRIBUTES>
 </CL_CI_TEST_DB_OPS_IN_LOOPS>
 <CL_CI_TEST_DCLS_CHK>
  <VERSION>000</VERSION>
  <ATTRIBUTES/>
 </CL_CI_TEST_DCLS_CHK>
 <CL_CI_TEST_DCLS_CHKOSM>
  <VERSION>000</VERSION>
  <ATTRIBUTES/>
 </CL_CI_TEST_DCLS_CHKOSM>
 <CL_CI_TEST_DCLS_COND>
  <VERSION>000</VERSION>
  <ATTRIBUTES/>
 </CL_CI_TEST_DCLS_COND>
 <CL_CI_TEST_DCLS_DDLS>
  <VERSION>000</VERSION>
  <ATTRIBUTES/>
 </CL_CI_TEST_DCLS_DDLS>
 <CL_CI_TEST_DDIC_CONSIST_AC>
  <VERSION>000</VERSION>
  <ATTRIBUTES>
   <CHECK_MESSAGE_IDS/>
  </ATTRIBUTES>
 </CL_CI_TEST_DDIC_CONSIST_AC>
 <CL_CI_TEST_DDIC_CONSIST_TA>
  <VERSION>000</VERSION>
  <ATTRIBUTES>
   <CHECK_MESSAGE_IDS/>
  </ATTRIBUTES>
 </CL_CI_TEST_DDIC_CONSIST_TA>
 <CL_CI_TEST_DDIC_TABLES>
  <VERSION>004</VERSION>
  <ATTRIBUTES>
   <PA_HDB_CHECKS></PA_HDB_CHECKS>
   <PA_INDEX>X</PA_INDEX>
   <PA_INDX_BUFFERED></PA_INDX_BUFFERED>
   <PA_TECH>X</PA_TECH>
   <PA_VIEW_CLIENT></PA_VIEW_CLIENT>
  </ATTRIBUTES>
 </CL_CI_TEST_DDIC_TABLES>
 <CL_CI_TEST_DDLS_ANNO>
  <VERSION>000</VERSION>
  <ATTRIBUTES/>
 </CL_CI_TEST_DDLS_ANNO>
 <CL_CI_TEST_DDLS_REF>
  <VERSION>000</VERSION>
  <ATTRIBUTES/>
 </CL_CI_TEST_DDLS_REF>
 <CL_CI_TEST_DDLX_SYNTAX_CHECK>
  <VERSION>000</VERSION>
  <ATTRIBUTES/>
 </CL_CI_TEST_DDLX_SYNTAX_CHECK>
 <CL_CI_TEST_EXOBJ_CHECK_IC>
  <VERSION>000</VERSION>
  <ATTRIBUTES/>
 </CL_CI_TEST_EXOBJ_CHECK_IC>
 <CL_CI_TEST_FIND_BADI_CALL>
  <VERSION>001</VERSION>
  <ATTRIBUTES>
   <P_NEW>X</P_NEW>
   <P_OLD></P_OLD>
   <P_UDAT>00000000</P_UDAT>
  </ATTRIBUTES>
 </CL_CI_TEST_FIND_BADI_CALL>
 <CL_CI_TEST_FIND_DYN_SQL>
  <VERSION>000</VERSION>
  <ATTRIBUTES>
   <ADBC_CLASSES>X</ADBC_CLASSES>
   <PER_MAIN_PROGRAM>X</PER_MAIN_PROGRAM>
   <PER_SINGLE_STMNT></PER_SINGLE_STMNT>
   <PER_SUB_ROUTINE></PER_SUB_ROUTINE>
   <PT_CLASSES/>
  </ATTRIBUTES>
 </CL_CI_TEST_FIND_DYN_SQL>
 <CL_CI_TEST_FOR_ALL_ENTRIES>
  <VERSION>002</VERSION>
  <ATTRIBUTES/>
 </CL_CI_TEST_FOR_ALL_ENTRIES>
 <CL_CI_TEST_FOR_ALL_ENTR_HANA>
  <VERSION>000</VERSION>
  <ATTRIBUTES>
   <PA_BUFF>X</PA_BUFF>
   <PA_EFFORT_ASSIGNS>10 </PA_EFFORT_ASSIGNS>
   <PA_EFFORT_CALLS>10 </PA_EFFORT_CALLS>
   <PA_LEVEL_EXTERN>1 </PA_LEVEL_EXTERN>
   <PA_ONLY_LOCAL>X</PA_ONLY_LOCAL>
   <PA_TABKAT>0 </PA_TABKAT>
   <PA_TABLES/>
  </ATTRIBUTES>
 </CL_CI_TEST_FOR_ALL_ENTR_HANA>
 <CL_CI_TEST_IMUD_NESTED>
  <VERSION>000</VERSION>
  <ATTRIBUTES/>
 </CL_CI_TEST_IMUD_NESTED>
 <CL_CI_TEST_IMUD_TAW_A>
  <VERSION>001</VERSION>
  <ATTRIBUTES>
   <PA_NOCLIENT>X</PA_NOCLIENT>
   <PA_NOFIELD></PA_NOFIELD>
   <PA_NOFIRST></PA_NOFIRST>
   <PA_NOWHERE>X</PA_NOWHERE>
  </ATTRIBUTES>
 </CL_CI_TEST_IMUD_TAW_A>
 <CL_CI_TEST_IMUD_TAW_SEC01>
  <VERSION>000</VERSION>
  <ATTRIBUTES>
   <PA_CLIENT>X</PA_CLIENT>
   <PA_DYNTAB>X</PA_DYNTAB>
   <PA_DYNWHERE>X</PA_DYNWHERE>
   <PA_TABLES/>
  </ATTRIBUTES>
 </CL_CI_TEST_IMUD_TAW_SEC01>
 <CL_CI_TEST_INT8>
  <VERSION>000</VERSION>
  <ATTRIBUTES>
   <PA_INVERTED></PA_INVERTED>
   <PA_LEVEL>0 </PA_LEVEL>
   <PA_LEVEL_EXTERN>1 </PA_LEVEL_EXTERN>
   <PA_ONLY_LOCAL>X</PA_ONLY_LOCAL>
   <PA_SHOW_DETAILS></PA_SHOW_DETAILS>
  </ATTRIBUTES>
 </CL_CI_TEST_INT8>
 <CL_CI_TEST_ITAB_PERFORMANCE>
  <VERSION>000</VERSION>
  <ATTRIBUTES>
   <PA_GENERIC>X</PA_GENERIC>
   <PA_HASHED>X</PA_HASHED>
   <PA_SORTED>X</PA_SORTED>
   <PA_STANDARD>X</PA_STANDARD>
  </ATTRIBUTES>
 </CL_CI_TEST_ITAB_PERFORMANCE>
 <CL_CI_TEST_LOOP_AT>
  <VERSION>002</VERSION>
  <ATTRIBUTES>
   <CHECK_FOR_HEADER_LINE>X</CHECK_FOR_HEADER_LINE>
   <CHECK_FOR_INTO_FS>X</CHECK_FOR_INTO_FS>
   <CHECK_FOR_INTO_WA>X</CHECK_FOR_INTO_WA>
   <ONLY_FOR_BROAD>X</ONLY_FOR_BROAD>
   <ONLY_WITH_MODIFY></ONLY_WITH_MODIFY>
   <ONLY_WITH_MODIFY_COMPAT></ONLY_WITH_MODIFY_COMPAT>
  </ATTRIBUTES>
 </CL_CI_TEST_LOOP_AT>
 <CL_CI_TEST_METRIC_LANGU_COMM>
  <VERSION>001</VERSION>
  <ATTRIBUTES>
   <MV_PA_CALC_N_ABAP_METRIC></MV_PA_CALC_N_ABAP_METRIC>
   <MV_PA_CALC_N_ENGL_METRIC></MV_PA_CALC_N_ENGL_METRIC>
   <MV_PA_CALC_N_GERM_METRIC></MV_PA_CALC_N_GERM_METRIC>
   <MV_PA_CALC_N_PCOM_METRIC></MV_PA_CALC_N_PCOM_METRIC>
   <MV_PA_CALC_N_UNKNOWN_METRIC></MV_PA_CALC_N_UNKNOWN_METRIC>
   <MV_PA_MIN_ROWS_ABAP_COMMENTS>2 </MV_PA_MIN_ROWS_ABAP_COMMENTS>
   <MV_PA_PCOM_RANGE/>
   <MV_PA_SEARCH_PSEUDOCOMMENTS></MV_PA_SEARCH_PSEUDOCOMMENTS>
   <MV_PA_WARN_ON_ABAP>X</MV_PA_WARN_ON_ABAP>
   <MV_PA_WARN_ON_GERMAN>X</MV_PA_WARN_ON_GERMAN>
  </ATTRIBUTES>
 </CL_CI_TEST_METRIC_LANGU_COMM>
 <CL_CI_TEST_METRIC_NOES>
  <VERSION>001</VERSION>
  <ATTRIBUTES>
   <MV_PA_COMM_MIN_LINES>10 </MV_PA_COMM_MIN_LINES>
   <MV_PA_COMM_ONLY_ENGLISH>X</MV_PA_COMM_ONLY_ENGLISH>
   <MV_PA_COMM_RATE></MV_PA_COMM_RATE>
   <MV_PA_NOES>X</MV_PA_NOES>
   <MV_PA_ON_DEV_OBJ_LEVEL></MV_PA_ON_DEV_OBJ_LEVEL>
   <MV_PA_SHOW_WARNING>X</MV_PA_SHOW_WARNING>
   <MV_PA_THRESHOLD_COMM_H>0 </MV_PA_THRESHOLD_COMM_H>
   <MV_PA_THRESHOLD_COMM_L>10 </MV_PA_THRESHOLD_COMM_L>
   <MV_PA_THRESHOLD_NOES_H>150 </MV_PA_THRESHOLD_NOES_H>
   <MV_PA_THRESHOLD_NOES_L>0 </MV_PA_THRESHOLD_NOES_L>
  </ATTRIBUTES>
 </CL_CI_TEST_METRIC_NOES>
 <CL_CI_TEST_MOVE_PERFORMANCE>
  <VERSION>000</VERSION>
  <ATTRIBUTES>
   <PA_BROAD_FIELD></PA_BROAD_FIELD>
   <PA_NESTED_TABLE>X</PA_NESTED_TABLE>
  </ATTRIBUTES>
 </CL_CI_TEST_MOVE_PERFORMANCE>
 <CL_CI_TEST_NO_ORDER_BY>
  <VERSION>000</VERSION>
  <ATTRIBUTES>
   <PA_ANALYZE_PC>X</PA_ANALYZE_PC>
   <PA_LEVEL_EXTERN>1 </PA_LEVEL_EXTERN>
   <PA_ONLY_LOCAL>X</PA_ONLY_LOCAL>
   <PA_QF_SYNTAX_CHECK></PA_QF_SYNTAX_CHECK>
   <PA_SHOW_DETAILS></PA_SHOW_DETAILS>
  </ATTRIBUTES>
 </CL_CI_TEST_NO_ORDER_BY>
 <CL_CI_TEST_ORA_RULE_HINT>
  <VERSION>001</VERSION>
  <ATTRIBUTES>
   <PA_SGL_MSG_PER_OBJ></PA_SGL_MSG_PER_OBJ>
  </ATTRIBUTES>
 </CL_CI_TEST_ORA_RULE_HINT>
 <CL_CI_TEST_PROXY>
  <VERSION>000</VERSION>
  <ATTRIBUTES>
   <T_ESR_CHECK>X</T_ESR_CHECK>
   <T_LOCAL_CHECK>X</T_LOCAL_CHECK>
  </ATTRIBUTES>
 </CL_CI_TEST_PROXY>
 <CL_CI_TEST_SADL_RUNTIME>
  <VERSION>000</VERSION>
  <ATTRIBUTES/>
 </CL_CI_TEST_SADL_RUNTIME>
 <CL_CI_TEST_SCAN_NESTED>
  <VERSION>000</VERSION>
  <ATTRIBUTES/>
 </CL_CI_TEST_SCAN_NESTED>
 <CL_CI_TEST_SEARCH_CDS_PRIV_ACC>
  <VERSION>000</VERSION>
  <ATTRIBUTES>
   <PA_TABLES/>
  </ATTRIBUTES>
 </CL_CI_TEST_SEARCH_CDS_PRIV_ACC>
 <CL_CI_TEST_SEARCH_DB_OPS>
  <VERSION>000</VERSION>
  <ATTRIBUTES>
   <PA_BUFF></PA_BUFF>
   <PA_CURSOR></PA_CURSOR>
   <PA_DELETE>X</PA_DELETE>
   <PA_EXEC></PA_EXEC>
   <PA_EXPORT></PA_EXPORT>
   <PA_IMPORT></PA_IMPORT>
   <PA_INSERT>X</PA_INSERT>
   <PA_MODIFY>X</PA_MODIFY>
   <PA_OBSOLETE_FORMS></PA_OBSOLETE_FORMS>
   <PA_SELECT></PA_SELECT>
   <PA_SELECT_UPD>X</PA_SELECT_UPD>
   <PA_TABLES>
    <ROW>
     <SIGN>E</SIGN>
     <OPTION>CP</OPTION>
     <LOW>Z*</LOW>
     <HIGH></HIGH>
    </ROW>
    <ROW>
     <SIGN>E</SIGN>
     <OPTION>CP</OPTION>
     <LOW>Y*</LOW>
     <HIGH></HIGH>
    </ROW>
   </PA_TABLES>
   <PA_UPDATE>X</PA_UPDATE>
  </ATTRIBUTES>
 </CL_CI_TEST_SEARCH_DB_OPS>
 <CL_CI_TEST_SEARCH_DB_OPS_IN_PC>
  <VERSION>000</VERSION>
  <ATTRIBUTES/>
 </CL_CI_TEST_SEARCH_DB_OPS_IN_PC>
 <CL_CI_TEST_SEARCH_STXH_ACCESS>
  <VERSION>000</VERSION>
  <ATTRIBUTES/>
 </CL_CI_TEST_SEARCH_STXH_ACCESS>
 <CL_CI_TEST_SELECT_EXIT>
  <VERSION>000</VERSION>
  <ATTRIBUTES>
   <P_EMPTY_SELECT>X</P_EMPTY_SELECT>
   <P_EXIT_IN_SELECT>X</P_EXIT_IN_SELECT>
   <P_SINGLE_ENTRY_ACCESSED></P_SINGLE_ENTRY_ACCESSED>
   <P_SKIP_UNIQUE_ACCESS></P_SKIP_UNIQUE_ACCESS>
   <P_UNBUFF_ONLY></P_UNBUFF_ONLY>
  </ATTRIBUTES>
 </CL_CI_TEST_SELECT_EXIT>
 <CL_CI_TEST_SELECT_TAW_A>
  <VERSION>000</VERSION>
  <ATTRIBUTES>
   <PA_NOCLIENT>X</PA_NOCLIENT>
   <PA_NOFIELD></PA_NOFIELD>
   <PA_NOFIRST></PA_NOFIRST>
   <PA_NOWHERE>X</PA_NOWHERE>
  </ATTRIBUTES>
 </CL_CI_TEST_SELECT_TAW_A>
 <CL_CI_TEST_SELECT_TAW_BYBUF>
  <VERSION>001</VERSION>
  <ATTRIBUTES/>
 </CL_CI_TEST_SELECT_TAW_BYBUF>
 <CL_CI_TEST_SELECT_TAW_SEC01>
  <VERSION>000</VERSION>
  <ATTRIBUTES>
   <PA_CLIENT>X</PA_CLIENT>
   <PA_DYNTAB>X</PA_DYNTAB>
   <PA_DYNWHERE>X</PA_DYNWHERE>
   <PA_TABLES/>
  </ATTRIBUTES>
 </CL_CI_TEST_SELECT_TAW_SEC01>
 <CL_CI_TEST_SELECT_WITH_DELETE>
  <VERSION>000</VERSION>
  <ATTRIBUTES/>
 </CL_CI_TEST_SELECT_WITH_DELETE>
 <CL_CI_TEST_SEQ_ACC_ITAB_NESTED>
  <VERSION>000</VERSION>
  <ATTRIBUTES>
   <P_INNER_LOOP_NO_WHERE></P_INNER_LOOP_NO_WHERE>
   <P_INNER_LOOP_SEQ>X</P_INNER_LOOP_SEQ>
   <P_INS_MOD_DEL>X</P_INS_MOD_DEL>
   <P_OTHERS></P_OTHERS>
   <P_OUTER_LOOP>X</P_OUTER_LOOP>
   <P_OUTER_OTHERS></P_OUTER_OTHERS>
   <P_OUTER_SELECT>X</P_OUTER_SELECT>
   <P_READ>X</P_READ>
   <P_SORT></P_SORT>
  </ATTRIBUTES>
 </CL_CI_TEST_SEQ_ACC_ITAB_NESTED>
 <CL_CI_TEST_SHO_CLIENT>
  <VERSION>000</VERSION>
  <ATTRIBUTES>
   <ATTACH_FOR_READ>X</ATTACH_FOR_READ>
   <ATTACH_FOR_UPDATE>X</ATTACH_FOR_UPDATE>
   <ATTACH_FOR_WRITE>X</ATTACH_FOR_WRITE>
   <DETACH_ALL_AREAS>X</DETACH_ALL_AREAS>
   <DETACH_AREA>X</DETACH_AREA>
   <FREE_AREA>X</FREE_AREA>
   <FREE_INSTANCE>X</FREE_INSTANCE>
   <INVALIDATE_AREA>X</INVALIDATE_AREA>
   <INVALIDATE_INSTANCE>X</INVALIDATE_INSTANCE>
   <PROPAGATE_AREA>X</PROPAGATE_AREA>
   <PROPAGATE_INSTANCE>X</PROPAGATE_INSTANCE>
  </ATTRIBUTES>
 </CL_CI_TEST_SHO_CLIENT>
 <CL_CI_TEST_SORT_IN_LOOP>
  <VERSION>000</VERSION>
  <ATTRIBUTES/>
 </CL_CI_TEST_SORT_IN_LOOP>
 <CL_CI_TEST_SQL1_CONSISTENCY>
  <VERSION>000</VERSION>
  <ATTRIBUTES/>
 </CL_CI_TEST_SQL1_CONSISTENCY>
 <CL_CI_TEST_SRVB_CONSISTENCY>
  <VERSION>000</VERSION>
  <ATTRIBUTES/>
 </CL_CI_TEST_SRVB_CONSISTENCY>
 <CL_CI_TEST_SYSUBRC>
  <VERSION>002</VERSION>
  <ATTRIBUTES>
   <PA_ANY/>
   <PA_AUTHORITY>X</PA_AUTHORITY>
   <PA_CALLE>X</PA_CALLE>
   <PA_CALLF>X</PA_CALLF>
   <PA_CALLM></PA_CALLM>
   <PA_DYNASSIGN></PA_DYNASSIGN>
   <PA_ENDCATCH>X</PA_ENDCATCH>
   <PA_IMUD>X</PA_IMUD>
   <PA_SELECT>X</PA_SELECT>
  </ATTRIBUTES>
 </CL_CI_TEST_SYSUBRC>
 <CL_CI_TEST_TYPE_CODES>
  <VERSION>000</VERSION>
  <ATTRIBUTES>
   <PA_D16N_D34N>X</PA_D16N_D34N>
   <PA_DATN_TIMN>X</PA_DATN_TIMN>
   <PA_GPT1_GGM1>X</PA_GPT1_GGM1>
   <PA_INT8>X</PA_INT8>
   <PA_INVERTED></PA_INVERTED>
   <PA_LEVEL>0 </PA_LEVEL>
   <PA_LEVEL_EXTERN>1 </PA_LEVEL_EXTERN>
   <PA_ONLY_LOCAL>X</PA_ONLY_LOCAL>
   <PA_SHOW_DETAILS></PA_SHOW_DETAILS>
   <PA_UTCL>X</PA_UTCL>
  </ATTRIBUTES>
 </CL_CI_TEST_TYPE_CODES>
 <CL_CI_TEST_USAB_GUI>
  <VERSION>000</VERSION>
  <ATTRIBUTES/>
 </CL_CI_TEST_USAB_GUI>
 <CL_CI_TEST_VALUE_PARAMETER>
  <VERSION>000</VERSION>
  <ATTRIBUTES>
   <PA_DEEP>X</PA_DEEP>
   <PA_EVENT></PA_EVENT>
   <PA_FLD></PA_FLD>
   <PA_LONG>X</PA_LONG>
   <PA_RETURN></PA_RETURN>
   <PA_STRING>X</PA_STRING>
   <PA_TABLE>X</PA_TABLE>
  </ATTRIBUTES>
 </CL_CI_TEST_VALUE_PARAMETER>
 <CL_CI_TEST_WORKFLOW>
  <VERSION>000</VERSION>
  <ATTRIBUTES>
   <MV_PACKAGE_CHECK></MV_PACKAGE_CHECK>
   <MV_WHITE_LIST_BLOCKED></MV_WHITE_LIST_BLOCKED>
  </ATTRIBUTES>
 </CL_CI_TEST_WORKFLOW>
 <CL_SAUNIT_LEGACY_CI_CHECK>
  <VERSION>000</VERSION>
  <ATTRIBUTES>
   <F_ALLOWED_DURATION_CATEGORY>12 </F_ALLOWED_DURATION_CATEGORY>
   <F_ALLOWED_RISK_LEVEL>11 </F_ALLOWED_RISK_LEVEL>
   <F_DURATION_CHECK_OPTION>2 </F_DURATION_CHECK_OPTION>
   <F_DURATION_SETTING>
    <CATEGORY_SHORT>60 </CATEGORY_SHORT>
    <CATEGORY_MEDIUM>300 </CATEGORY_MEDIUM>
    <CATEGORY_LONG>3600 </CATEGORY_LONG>
   </F_DURATION_SETTING>
  </ATTRIBUTES>
 </CL_SAUNIT_LEGACY_CI_CHECK>
 <ZCL_PE_ATC_ABAP_NAMING_NEW>
  <VERSION>000</VERSION>
  <ATTRIBUTES>
   <M_OPTION></M_OPTION>
   <M_SELSCR/>
   <M_SETUP>
    <PREFIX_ELEMENTARY>V</PREFIX_ELEMENTARY>
    <PREFIX_GENERIC>[VSTO]</PREFIX_GENERIC>
    <PREFIX_STRUCTURE>S</PREFIX_STRUCTURE>
    <PREFIX_TABLE_ANY>T</PREFIX_TABLE_ANY>
    <PREFIX_TABLE_HASHED>TH</PREFIX_TABLE_HASHED>
    <PREFIX_TABLE_INDEX>T</PREFIX_TABLE_INDEX>
    <PREFIX_TABLE_STANDARD>[TR]</PREFIX_TABLE_STANDARD>
    <PREFIX_TABLE_SORTED>TS</PREFIX_TABLE_SORTED>
    <PREFIX_REF_DATA>O</PREFIX_REF_DATA>
    <PREFIX_REF_CLASS>O</PREFIX_REF_CLASS>
    <PREFIX_REF_CLASS_BADI>O</PREFIX_REF_CLASS_BADI>
    <PREFIX_REF_CLASS_EXCEPTION>O</PREFIX_REF_CLASS_EXCEPTION>
    <PREFIX_REF_INTERFACE>IF</PREFIX_REF_INTERFACE>
    <PATTERNS_CLAS_NAME_GLOBAL>
     <ROW>ZCX_(FI|HR|MF|SP|SD|SC|PE|IS|AM|BW|PD)_</ROW>
     <ROW>ZCL_(FI|HR|MF|SP|SD|SC|PE|IS|AM|BW|IM)_</ROW>
     <ROW>ZCL_PD_</ROW>
     <ROW>ZBP_(FI|HR|MF|SP|SD|SC|PE|IS|AM|BW|PD)_</ROW>
    </PATTERNS_CLAS_NAME_GLOBAL>
    <PATTERNS_CLAS_NAME_LOCAL>
     <ROW>L(CL|CX|TC|TD|HC|SC)</ROW>
    </PATTERNS_CLAS_NAME_LOCAL>
    <PATTERNS_CLAS_MEMBER>
     <ROW>[GM][:type:]_</ROW>
    </PATTERNS_CLAS_MEMBER>
    <PATTERNS_CLAS_MEMBER_CLASS>
     <ROW>G[:type:]_</ROW>
    </PATTERNS_CLAS_MEMBER_CLASS>
    <PATTERNS_CLAS_CONSTANT>
     <ROW>[GM]C_</ROW>
    </PATTERNS_CLAS_CONSTANT>
    <PATTERNS_CLAS_TYPE>
     <ROW>[GM]TYP_</ROW>
    </PATTERNS_CLAS_TYPE>
    <PATTERNS_INTF_NAME_GLOBAL>
     <ROW>ZIF_(FI|HR|MF|SP|SD|SC|PE|IS|AM|BW|PD)_</ROW>
     <ROW>ZIF_II_</ROW>
    </PATTERNS_INTF_NAME_GLOBAL>
    <PATTERNS_INTF_NAME_LOCAL>
     <ROW>LIF_</ROW>
    </PATTERNS_INTF_NAME_LOCAL>
    <PATTERNS_INTF_MEMBER>
     <ROW>[GM][:type:]_</ROW>
    </PATTERNS_INTF_MEMBER>
    <PATTERNS_INTF_MEMBER_CLASS>
     <ROW>G[:type:]_</ROW>
    </PATTERNS_INTF_MEMBER_CLASS>
    <PATTERNS_INTF_CONSTANT>
     <ROW>[GM]C_</ROW>
    </PATTERNS_INTF_CONSTANT>
    <PATTERNS_INTF_TYPE>
     <ROW>[GM]TYP_</ROW>
    </PATTERNS_INTF_TYPE>
    <PATTERNS_METD_NAME/>
    <PATTERNS_METD_IMPORTING>
     <ROW>I[:type:]_</ROW>
    </PATTERNS_METD_IMPORTING>
    <PATTERNS_METD_EXPORTING>
     <ROW>E[:type:]_</ROW>
    </PATTERNS_METD_EXPORTING>
    <PATTERNS_METD_CHANGING>
     <ROW>C[:type:]_</ROW>
    </PATTERNS_METD_CHANGING>
    <PATTERNS_METD_RETURNING>
     <ROW>R[:type:]_</ROW>
    </PATTERNS_METD_RETURNING>
    <PATTERNS_EVNT_NAME/>
    <PATTERNS_EVNT_EXPORTING>
     <ROW>E[:type:]_</ROW>
    </PATTERNS_EVNT_EXPORTING>
    <PATTERNS_FUGR_NAME>
     <ROW>Z(FI|HR|MF|SP|SD|SC|PE|IS|AM|BW|PD)_FG_</ROW>
    </PATTERNS_FUGR_NAME>
    <PATTERNS_FUNC_NAME>
     <ROW>Z(FI|HR|MF|SP|SD|SC|PE|IS|AM|BW)_FM_</ROW>
     <ROW>ZPD_FM_</ROW>
    </PATTERNS_FUNC_NAME>
    <PATTERNS_FUNC_IMPORTING>
     <ROW>I[:type:]_</ROW>
    </PATTERNS_FUNC_IMPORTING>
    <PATTERNS_FUNC_EXPORTING>
     <ROW>E[:type:]_</ROW>
    </PATTERNS_FUNC_EXPORTING>
    <PATTERNS_FUNC_CHANGING>
     <ROW>C[:type:]_</ROW>
    </PATTERNS_FUNC_CHANGING>
    <PATTERNS_FUNC_TABLES>
     <ROW>T_</ROW>
    </PATTERNS_FUNC_TABLES>
    <PATTERNS_REPT_NAME>
     <ROW>Z(FI|HR|MF|SP|SD|SC|PE|IS|AM|BW)_[RIOP]_</ROW>
     <ROW>ZPD_[RIOP]_</ROW>
    </PATTERNS_REPT_NAME>
    <PATTERNS_PROG_DATA_LOCAL>
     <ROW>L[:type:]_</ROW>
    </PATTERNS_PROG_DATA_LOCAL>
    <PATTERNS_PROG_DATA_GLOBAL>
     <ROW>G[:type:]_</ROW>
    </PATTERNS_PROG_DATA_GLOBAL>
    <PATTERNS_PROG_DATA_STATIC>
     <ROW>S[:type:]_</ROW>
    </PATTERNS_PROG_DATA_STATIC>
    <PATTERNS_PROG_FIELD_SYMBOL_LOC>
     <ROW>&lt;L[:type:]_</ROW>
    </PATTERNS_PROG_FIELD_SYMBOL_LOC>
    <PATTERNS_PROG_FIELD_SYMBOL_GLB>
     <ROW>&lt;G[:type:]_</ROW>
    </PATTERNS_PROG_FIELD_SYMBOL_GLB>
    <PATTERNS_PROG_CONSTANT_LOCAL>
     <ROW>LC_</ROW>
    </PATTERNS_PROG_CONSTANT_LOCAL>
    <PATTERNS_PROG_CONSTANT_GLOBAL>
     <ROW>GC_</ROW>
    </PATTERNS_PROG_CONSTANT_GLOBAL>
    <PATTERNS_PROG_FIELD_GROUP/>
    <PATTERNS_PROG_SELSCR_OPTION>
     <ROW>S_</ROW>
    </PATTERNS_PROG_SELSCR_OPTION>
    <PATTERNS_PROG_SELSCR_PARAMETER>
     <ROW>P_</ROW>
     <ROW>CB_</ROW>
     <ROW>RB_</ROW>
    </PATTERNS_PROG_SELSCR_PARAMETER>
    <PATTERNS_PROG_TYPE_LOCAL>
     <ROW>LTYP_</ROW>
    </PATTERNS_PROG_TYPE_LOCAL>
    <PATTERNS_PROG_TYPE_GLOBAL>
     <ROW>GTYP_</ROW>
    </PATTERNS_PROG_TYPE_GLOBAL>
    <PATTERNS_PROG_DEFINE/>
    <PATTERNS_FORM_NAME/>
    <PATTERNS_FORM_USING>
     <ROW>U[:type:]_</ROW>
    </PATTERNS_FORM_USING>
    <PATTERNS_FORM_CHANGING>
     <ROW>C[:type:]_</ROW>
    </PATTERNS_FORM_CHANGING>
    <PATTERNS_FORM_TABLE>
     <ROW>T_</ROW>
    </PATTERNS_FORM_TABLE>
   </M_SETUP>
  </ATTRIBUTES>
 </ZCL_PE_ATC_ABAP_NAMING_NEW>
 <ZCL_PE_ATC_AOC_CHECK_01>
  <VERSION>001</VERSION>
  <ATTRIBUTES>
   <MV_ERRTY>W</MV_ERRTY>
  </ATTRIBUTES>
 </ZCL_PE_ATC_AOC_CHECK_01>
 <ZCL_PE_ATC_AOC_CHECK_22>
  <VERSION>001</VERSION>
  <ATTRIBUTES>
   <MV_ERRTY>E</MV_ERRTY>
  </ATTRIBUTES>
 </ZCL_PE_ATC_AOC_CHECK_22>
 <ZCL_PE_ATC_AOC_CHECK_24>
  <VERSION>001</VERSION>
  <ATTRIBUTES>
   <MV_ERRTY>E</MV_ERRTY>
   <MV_STATEMENTS>50 </MV_STATEMENTS>
  </ATTRIBUTES>
 </ZCL_PE_ATC_AOC_CHECK_24>
 <ZCL_PE_ATC_AOC_CHECK_33>
  <VERSION>001</VERSION>
  <ATTRIBUTES>
   <MV_ERRTY>E</MV_ERRTY>
  </ATTRIBUTES>
 </ZCL_PE_ATC_AOC_CHECK_33>
 <ZCL_PE_ATC_AOC_CHECK_40>
  <VERSION>001</VERSION>
  <ATTRIBUTES>
   <MV_ERRTY>W</MV_ERRTY>
  </ATTRIBUTES>
 </ZCL_PE_ATC_AOC_CHECK_40>
 <ZCL_PE_ATC_AOC_CHECK_42>
  <VERSION>001</VERSION>
  <ATTRIBUTES>
   <MV_ERRTY>E</MV_ERRTY>
  </ATTRIBUTES>
 </ZCL_PE_ATC_AOC_CHECK_42>
 <ZCL_PE_ATC_CHANGE_LOG_ABAP>
  <VERSION>001</VERSION>
  <ATTRIBUTES/>
 </ZCL_PE_ATC_CHANGE_LOG_ABAP>
 <ZCL_PE_ATC_CHANGE_LOG_RAP>
  <VERSION>001</VERSION>
  <ATTRIBUTES/>
 </ZCL_PE_ATC_CHANGE_LOG_RAP>
 <ZCL_PE_ATC_CHECK_TABLE_LOG>
  <VERSION>000</VERSION>
  <ATTRIBUTES>
   <MT_FIELD>
    <ROW>ZPE_S_TABLE_LOGGING</ROW>
   </MT_FIELD>
  </ATTRIBUTES>
 </ZCL_PE_ATC_CHECK_TABLE_LOG>
 <ZCL_PE_ATC_CODE_REVIEW>
  <VERSION>001</VERSION>
  <ATTRIBUTES>
   <MT_TRUSTED/>
  </ATTRIBUTES>
 </ZCL_PE_ATC_CODE_REVIEW>
 <ZCL_PE_ATC_EXTENDED_CHECK>
  <VERSION>001</VERSION>
  <ATTRIBUTES>
   <CUSTOM_CHECK>X</CUSTOM_CHECK>
   <FLAGS>
    <X_PER>X</X_PER>
    <X_CAL>X</X_CAL>
    <X_DAT>X</X_DAT>
    <X_OPF>X</X_OPF>
    <X_UNR>X</X_UNR>
    <X_GES>X</X_GES>
    <X_MES>X</X_MES>
    <X_PFS>X</X_PFS>
    <X_BRE>X</X_BRE>
    <X_WOO>X</X_WOO>
    <X_WRN>X</X_WRN>
    <X_STE>X</X_STE>
    <X_TXT>X</X_TXT>
    <X_AUT>X</X_AUT>
    <X_SUB>X</X_SUB>
    <X_LOA>X</X_LOA>
    <X_MLS>X</X_MLS>
    <X_PUT>X</X_PUT>
    <X_HEL>X</X_HEL>
    <X_SEC></X_SEC>
   </FLAGS>
   <STANDARD_CHECK></STANDARD_CHECK>
   <TRANSPORT_CHECK></TRANSPORT_CHECK>
  </ATTRIBUTES>
 </ZCL_PE_ATC_EXTENDED_CHECK>
 <ZCL_PE_ATC_GUIDELINES>
  <VERSION>001</VERSION>
  <ATTRIBUTES/>
 </ZCL_PE_ATC_GUIDELINES>
 <ZCL_PE_ATC_GUIDELINES_RAP>
  <VERSION>001</VERSION>
  <ATTRIBUTES/>
 </ZCL_PE_ATC_GUIDELINES_RAP>
 <ZCL_PE_ATC_HARDCODE_DETECTOR>
  <VERSION>000</VERSION>
  <ATTRIBUTES>
   <_DICT_OF_LITERALS>
    <ROW>
     <SIGN>I</SIGN>
     <OPTION>EQ</OPTION>
     <LOW>0</LOW>
     <HIGH></HIGH>
    </ROW>
    <ROW>
     <SIGN>I</SIGN>
     <OPTION>EQ</OPTION>
     <LOW>INTERN</LOW>
     <HIGH></HIGH>
    </ROW>
    <ROW>
     <SIGN>I</SIGN>
     <OPTION>EQ</OPTION>
     <LOW>0123456789</LOW>
     <HIGH></HIGH>
    </ROW>
    <ROW>
     <SIGN>I</SIGN>
     <OPTION>EQ</OPTION>
     <LOW>$TEMP</LOW>
     <HIGH></HIGH>
    </ROW>
    <ROW>
     <SIGN>I</SIGN>
     <OPTION>EQ</OPTION>
     <LOW>HTML</LOW>
     <HIGH></HIGH>
    </ROW>
    <ROW>
     <SIGN>I</SIGN>
     <OPTION>EQ</OPTION>
     <LOW>TXT</LOW>
     <HIGH></HIGH>
    </ROW>
    <ROW>
     <SIGN>I</SIGN>
     <OPTION>EQ</OPTION>
     <LOW>TEXT</LOW>
     <HIGH></HIGH>
    </ROW>
    <ROW>
     <SIGN>I</SIGN>
     <OPTION>EQ</OPTION>
     <LOW>YES</LOW>
     <HIGH></HIGH>
    </ROW>
    <ROW>
     <SIGN>I</SIGN>
     <OPTION>EQ</OPTION>
     <LOW>IEQ</LOW>
     <HIGH></HIGH>
    </ROW>
    <ROW>
     <SIGN>I</SIGN>
     <OPTION>EQ</OPTION>
     <LOW>ICP</LOW>
     <HIGH></HIGH>
    </ROW>
    <ROW>
     <SIGN>I</SIGN>
     <OPTION>EQ</OPTION>
     <LOW>ZCURR</LOW>
     <HIGH></HIGH>
    </ROW>
    <ROW>
     <SIGN>I</SIGN>
     <OPTION>EQ</OPTION>
     <LOW>Not_Applicable</LOW>
     <HIGH></HIGH>
    </ROW>
    <ROW>
     <SIGN>I</SIGN>
     <OPTION>CP</OPTION>
     <LOW>*?*</LOW>
     <HIGH></HIGH>
    </ROW>
    <ROW>
     <SIGN>I</SIGN>
     <OPTION>CP</OPTION>
     <LOW>*$*</LOW>
     <HIGH></HIGH>
    </ROW>
    <ROW>
     <SIGN>I</SIGN>
     <OPTION>CP</OPTION>
     <LOW>*(*</LOW>
     <HIGH></HIGH>
    </ROW>
    <ROW>
     <SIGN>I</SIGN>
     <OPTION>CP</OPTION>
     <LOW>*)*</LOW>
     <HIGH></HIGH>
    </ROW>
    <ROW>
     <SIGN>I</SIGN>
     <OPTION>CP</OPTION>
     <LOW>@*@</LOW>
     <HIGH></HIGH>
    </ROW>
   </_DICT_OF_LITERALS>
   <_DICT_OF_RELATED_OPERAND>
    <ROW>
     <SIGN>I</SIGN>
     <OPTION>CP</OPTION>
     <LOW>*-OPTION</LOW>
     <HIGH></HIGH>
    </ROW>
    <ROW>
     <SIGN>I</SIGN>
     <OPTION>CP</OPTION>
     <LOW>*-SIGN</LOW>
     <HIGH></HIGH>
    </ROW>
   </_DICT_OF_RELATED_OPERAND>
   <_LITERAL_MAX_LENGHT>18 </_LITERAL_MAX_LENGHT>
   <_LITERAL_MIN_LENGHT>2 </_LITERAL_MIN_LENGHT>
  </ATTRIBUTES>
 </ZCL_PE_ATC_HARDCODE_DETECTOR>
 <ZCL_PE_ATC_NAMING_CONVENTION>
  <VERSION>001</VERSION>
  <ATTRIBUTES>
   <MT_DDLS>
    <ROW>Z&lt;AREA&gt;_I_*</ROW>
    <ROW>Z&lt;AREA&gt;_C_*</ROW>
    <ROW>Z&lt;AREA&gt;_E_*</ROW>
    <ROW>Z&lt;AREA&gt;_X_*</ROW>
    <ROW>Z&lt;AREA&gt;_A_*</ROW>
    <ROW>Z&lt;AREA&gt;_D_*</ROW>
   </MT_DDLS>
   <MT_DDLX>
    <ROW>Z&lt;AREA&gt;_C_*</ROW>
   </MT_DDLX>
   <MT_SAP_AREA>
    <ROW>AM</ROW>
    <ROW>FI</ROW>
    <ROW>HR</ROW>
    <ROW>IS</ROW>
    <ROW>MF</ROW>
    <ROW>SP</ROW>
    <ROW>SD</ROW>
    <ROW>SC</ROW>
    <ROW>PE</ROW>
    <ROW>BW</ROW>
    <ROW>PD</ROW>
    <ROW>Z1</ROW>
   </MT_SAP_AREA>
   <MT_SRVB>
    <ROW>Z&lt;AREA&gt;_UI_*</ROW>
    <ROW>Z&lt;AREA&gt;_API_*</ROW>
   </MT_SRVB>
   <MT_TABL_APPEND>
    <ROW>ZZ*</ROW>
   </MT_TABL_APPEND>
   <MT_TABL_INTTAB>
    <ROW>Z&lt;AREA&gt;_S_*</ROW>
    <ROW>Z&lt;AREA&gt;_AIF_*</ROW>
   </MT_TABL_INTTAB>
   <MT_TABL_TRANSP>
    <ROW>Z&lt;AREA&gt;_T_*</ROW>
   </MT_TABL_TRANSP>
   <MT_TTYP>
    <ROW>Z&lt;AREA&gt;_TT_*</ROW>
    <ROW>Z&lt;AREA&gt;_AIF_*</ROW>
   </MT_TTYP>
   <MV_DOMA>Z&lt;AREA&gt;_*</MV_DOMA>
   <MV_DTEL>Z&lt;AREA&gt;_*</MV_DTEL>
   <MV_ENHO>Z&lt;AREA&gt;_EI_*</MV_ENHO>
   <MV_ENHS>Z&lt;AREA&gt;_ES_*</MV_ENHS>
   <MV_MSAG>Z&lt;AREA&gt;_*</MV_MSAG>
   <MV_SFPF>Z&lt;AREA&gt;_*</MV_SFPF>
   <MV_SFPI>Z&lt;AREA&gt;_*</MV_SFPI>
   <MV_SHLP>Z&lt;AREA&gt;_*</MV_SHLP>
   <MV_SRVD>Z&lt;AREA&gt;_*</MV_SRVD>
   <MV_VIEW>Z&lt;AREA&gt;_V_*</MV_VIEW>
  </ATTRIBUTES>
 </ZCL_PE_ATC_NAMING_CONVENTION>
 <ZCL_PE_ATC_OBSOLETE_OBJECTS>
  <VERSION>000</VERSION>
  <ATTRIBUTES>
   <MT_OBSOLETES>
    <ROW>SSFO</ROW>
    <ROW>SSST</ROW>
    <ROW>IWMO</ROW>
    <ROW>IWOM</ROW>
    <ROW>IWPR</ROW>
    <ROW>IWSC</ROW>
    <ROW>IWSG</ROW>
    <ROW>IWSV</ROW>
    <ROW>IWVB</ROW>
    <ROW>IWVO</ROW>
    <ROW>WDCA</ROW>
    <ROW>WDCP</ROW>
    <ROW>WDRC</ROW>
    <ROW>WDRP</ROW>
    <ROW>WDYA</ROW>
    <ROW>WDYL</ROW>
    <ROW>WDYN</ROW>
    <ROW>FORM</ROW>
    <ROW>STYL</ROW>
    <ROW>SFRH</ROW>
   </MT_OBSOLETES>
  </ATTRIBUTES>
 </ZCL_PE_ATC_OBSOLETE_OBJECTS>
 <ZCL_PE_ATC_PACKAGE_CHECK>
  <VERSION>001</VERSION>
  <ATTRIBUTES>
   <GV_CHANGES>X</GV_CHANGES>
  </ATTRIBUTES>
 </ZCL_PE_ATC_PACKAGE_CHECK>
 <ZCL_PE_ATC_PRAGMA_COUNTER>
  <VERSION>001</VERSION>
  <ATTRIBUTES>
   <MV_MAX_NUMBER>3 </MV_MAX_NUMBER>
  </ATTRIBUTES>
 </ZCL_PE_ATC_PRAGMA_COUNTER>
 <ZCL_PE_ATC_UNREFERENCED_DDIC>
  <VERSION>000</VERSION>
  <ATTRIBUTES/>
 </ZCL_PE_ATC_UNREFERENCED_DDIC>
 <ZCL_PE_ATC_UNREFERENCED_MSG>
  <VERSION>001</VERSION>
  <ATTRIBUTES>
   <MV_ERRTY>W</MV_ERRTY>
  </ATTRIBUTES>
 </ZCL_PE_ATC_UNREFERENCED_MSG>
</VARIANT>
